CHANGELOG.md
LICENSE
MANIFEST.in
README.md
setup.cfg
setup.py
pip_services_data/IFilteredPageReader.py
pip_services_data/IFilteredReader.py
pip_services_data/IGetter.py
pip_services_data/ILoader.py
pip_services_data/IPartialUpdater.py
pip_services_data/IQuerablePageReader.py
pip_services_data/IQuerableReader.py
pip_services_data/ISaver.py
pip_services_data/ISetter.py
pip_services_data/IWriter.py
pip_services_data/__init__.py
pip_services_data.egg-info/PKG-INFO
pip_services_data.egg-info/SOURCES.txt
pip_services_data.egg-info/dependency_links.txt
pip_services_data.egg-info/requires.txt
pip_services_data.egg-info/top_level.txt
pip_services_data.egg-info/zip-safe
pip_services_data/file/FilePersistence.py
pip_services_data/file/IdentifiableFilePersistence.py
pip_services_data/file/JsonFilePersister.py
pip_services_data/file/__init__.py
pip_services_data/memory/IdentifiableMemoryPersistence.py
pip_services_data/memory/MemoryPersistence.py
pip_services_data/memory/__init__.py
pip_services_data/mongodb/IdentifiableMongoDbPersistence.py
pip_services_data/mongodb/MongoDbPersistence.py
pip_services_data/mongodb/__init__.py
test/Dummy.py
test/DummyPersistenceFixture.py
test/IDummyPersistence.py
test/__init__.py
test/file/DummyFilePersistence.py
test/file/__init__.py
test/file/test_DummyFilePersistence.py
test/memory/DummyMemoryPersistence.py
test/memory/__init__.py
test/memory/test_DummyMemoryPersistence.py
test/mongodb/DummyMongoDbPersistence.py
test/mongodb/__init__.py
test/mongodb/test_DummyMongoDbPersistence.py